dataclassy/__init__.py
dataclassy/dataclass.py
dataclassy/decorator.py
dataclassy/functions.py
dataclassy/mypy.py
dataclassy/py.typed
dataclassy-0.10.4.dist-info/LICENSE.md
dataclassy-0.10.4.dist-info/METADATA
dataclassy-0.10.4.dist-info/WHEEL
dataclassy-0.10.4.dist-info/top_level.txt
dataclassy-0.10.4.dist-info/RECORD
