Metadata-Version: 2.1
Name: dataclassy
Version: 0.10.4
Summary: A fast and flexible reimplementation of data classes
Home-page: https://github.com/biqqles/dataclassy
Author: biqqles
Author-email: biqqles@protonmail.com
License: UNKNOWN
Platform: UNKNOWN
Classifier: Programming Language :: Python :: 3
Classifier: License :: OSI Approved :: Mozilla Public License 2.0 (MPL 2.0)
Classifier: Operating System :: OS Independent
Classifier: Development Status :: 4 - Beta
Classifier: Programming Language :: Python :: Implementation :: CPython
Classifier: Programming Language :: Python :: Implementation :: PyPy
Requires-Python: >=3.6
